carriers/__init__.py
carriers/app/__init__.py
carriers/app/additional_settings.py
carriers/app/carrier_integration_test.py
carriers/app/constants.py
carriers/app/mongo.py
carriers/app/utils.py
carriers/app/consolidation/__init__.py
carriers/app/consolidation/attribute_mapping.py
carriers/app/consolidation/carrier_integration_base.py
carriers/app/consolidation/common_config.py
carriers/app/consolidation/airwayscourier/__init__.py
carriers/app/consolidation/airwayscourier/airwayscourier.py
carriers/app/consolidation/blitz/__init__.py
carriers/app/consolidation/blitz/blitz.py
carriers/app/consolidation/utilization/__init__.py
carriers/app/consolidation/utilization/db_operations.py
carriers/app/consolidation/utilization/final_order_db_updator.py
carriers/app/consolidation/utilization/generic_order_id_generator.py
carriers/app/consolidation/utilization/get_awb.py
carriers/app/consolidation/utilization/pdf_merger.py
carriers/app/consolidation/utilization/pdf_split.py
carriers/app/consolidation/utilization/s3_aws_ops.py
carriers/app/consolidation/utilization/timed_cache.py
carriers/app/consolidation/utilization/utils.py
carriers/app/consolidation/utilization/utils2.py
carrier_integrations1-0.1.4.dist-info/METADATA
carrier_integrations1-0.1.4.dist-info/WHEEL
carrier_integrations1-0.1.4.dist-info/top_level.txt
carrier_integrations1-0.1.4.dist-info/RECORD
